README.md
setup.py
Ayra/__init__.py
Ayra/__main__.py
Ayra/configs.py
Ayra/exceptions.py
Ayra/kynan.py
Ayra/loader.py
Ayra/version.py
Ayra/_misc/__init__.py
Ayra/_misc/_assistant.py
Ayra/_misc/_decorators.py
Ayra/_misc/_supporter.py
Ayra/_misc/_wrappers.py
Ayra/dB/__init__.py
Ayra/dB/_core.py
Ayra/dB/afk_db.py
Ayra/dB/antiflood_db.py
Ayra/dB/asst_fns.py
Ayra/dB/asstcmd_db.py
Ayra/dB/autoban_db.py
Ayra/dB/blacklist_chat_db.py
Ayra/dB/blacklist_db.py
Ayra/dB/botchat_db.py
Ayra/dB/broadcast_db.py
Ayra/dB/ch_db.py
Ayra/dB/dnd_db.py
Ayra/dB/echo_db.py
Ayra/dB/filestore_db.py
Ayra/dB/filter_db.py
Ayra/dB/forcesub_db.py
Ayra/dB/gban_mute_db.py
Ayra/dB/gcast_blacklist_db.py
Ayra/dB/greetings_db.py
Ayra/dB/logusers_db.py
Ayra/dB/mute_db.py
Ayra/dB/night_db.py
Ayra/dB/notes_db.py
Ayra/dB/nsfw_db.py
Ayra/dB/pmpermit_db.py
Ayra/dB/snips_db.py
Ayra/dB/vc_sudos.py
Ayra/dB/warn_db.py
Ayra/fns/FastTelethon.py
Ayra/fns/__init__.py
Ayra/fns/admins.py
Ayra/fns/executor.py
Ayra/fns/gDrive.py
Ayra/fns/google_image.py
Ayra/fns/helper.py
Ayra/fns/info.py
Ayra/fns/misc.py
Ayra/fns/tools.py
Ayra/fns/ytdl.py
Ayra/startup/BaseClient.py
Ayra/startup/__init__.py
Ayra/startup/_database.py
Ayra/startup/_extra.py
Ayra/startup/connections.py
Ayra/startup/funcs.py
Ayra/startup/loader.py
Ayra/startup/utils.py
kanjut.egg-info/PKG-INFO
kanjut.egg-info/SOURCES.txt
kanjut.egg-info/dependency_links.txt
kanjut.egg-info/requires.txt
kanjut.egg-info/top_level.txt