Metadata-Version: 2.1
Name: kanjut
Version: 2.1.2
Summary: Client library for opet
Home-page: https://github.com/opet321/nayu
Author: Unknown
Author-email: opetbae6@gmail.com
License: AGPL
Keywords: pypi,mengontol,python,telethon,telebot
Platform: UNKNOWN
Classifier: Development Status :: 3 - Alpha
Classifier: Intended Audience :: Developers
Classifier: Programming Language :: Python :: 3
Classifier: Operating System :: Unix
